Workbook

Sheet DATASET
A1: product_id | B1: Product | C1: category | D1: product type | E1: actual_price | F1: discounted_price | G1: expected revenue | H1: actual revenue | I1: discount given | J1: profit/loss | K1: discount_percentage | L1: rating | M1: rating_count | N1: User | O1: no. of users | P1: Image link | Q1: productlink
A2: B07JW9H4J1 | B2: Wayona Nylon Braided USB | C2: Cables&Accessories | D2: Cables | E2: 1099 | F2: 399 | G2: =E2*O2 -> 4396 | H2: =F2*O2 -> 1596 | I2: =(E2*K2)*O2 -> 2813.44 | J2: =H2-G2 -> -2800 | K2: 0.64 | L2: 4.2 | M2: 24269 | N2: Manav,Adarsh gupta,Sundeep,S.Sayeed | O2: =LEN(N2)-LEN(SUBSTITUTE(N2,",",""))+1 -> 4 | P2: =HYPERLINK(#REF!,"Link") -> #REF! | Q2: =HYPERLINK(#REF!,"Link") -> #REF!
A3: B098NS6PVG | B3: Ambrane Unbreakable 60W / | C3: NetworkAdapters | D3: WirelessUSBAdapters | E3: 349 | F3: 199 | G3: =E3*O3 -> 1047 | H3: =F3*O3 -> 597 | I3: =(E3*K3)*O3 -> 450.21 | J3: =H3-G3 -> -450 | K3: 0.43 | L3: 4 | M3: 43994 | N3: ArdKn,Nirbhay kumar,Sagar | O3: =LEN(N3)-LEN(SUBSTITUTE(N3,",",""))+1 -> 3 | P3: =HYPERLINK(#REF!,"Link") -> #REF! | Q3: =HYPERLINK(#REF!,"Link") -> #REF!
A4: B096MSW6CT | B4: Sounce Fast Phone Charging | C4: Accessories | D4: Cables | E4: 1899 | F4: 199 | G4: =E4*O4 -> 9495 | H4: =F4*O4 -> 995 | I4: =(E4*K4)*O4 -> 8545.5 | J4: =H4-G4 -> -8500 | K4: 0.9 | L4: 3.9 | M4: 7928 | N4: Kunal,Himanshu,viswanath,sai niharka,saqib | O4: =LEN(N4)-LEN(SUBSTITUTE(N4,",",""))+1 -> 5 | P4: =HYPERLINK(#REF!,"Link") -> #REF! | Q4: =HYPERLINK(#REF!,"Link") -> #REF!
A5: B08HDJ86NZ | B5: boAt Deuce USB 300 | C5: Televisions | D5: SmartTelevisions | E5: 699 | F5: 329 | G5: =E5*O5 -> 2796 | H5: =F5*O5 -> 1316 | I5: =(E5*K5)*O5 -> 1481.88 | J5: =H5-G5 -> -1480 | K5: 0.53 | L5: 4.2 | M5: 94363 | N5: Omkar dhale,JD,HEMALATHA,Ajwadh | O5: =LEN(N5)-LEN(SUBSTITUTE(N5,",",""))+1 -> 4 | P5: =HYPERLINK(#REF!,"Link") -> #REF! | Q5: =HYPERLINK(#REF!,"Link") -> #REF!
A6: B08CF3B7N1 | B6: Portronics Konnect L 1.2M | C6: Accessories | D6: RemoteControls | E6: 399 | F6: 154 | G6: =E6*O6 -> 1197 | H6: =F6*O6 -> 462 | I6: =(E6*K6)*O6 -> 730.17 | J6: =H6-G6 -> -735 | K6: 0.61 | L6: 4.2 | M6: 16905 | N6: rahuls6099,Swasat Borah,Ajay | O6: =LEN(N6)-LEN(SUBSTITUTE(N6,",",""))+1 -> 3 | P6: =HYPERLINK(#REF!,"Link") -> #REF! | Q6: =HYPERLINK(#REF!,"Link") -> #REF!
A7: B08Y1TFSP6 | B7: pTron Solero TB301 3A | C7: Televisions | D7: StandardTelevisions | E7: 1000 | F7: 149 | G7: =E7*O7 -> 4000 | H7: =F7*O7 -> 596 | I7: =(E7*K7)*O7 -> 3400 | J7: =H7-G7 -> -3404 | K7: 0.85 | L7: 3.9 | M7: 24871 | N7: Jayesh,Rajesh k.,Soopy,amazon | O7: =LEN(N7)-LEN(SUBSTITUTE(N7,",",""))+1 -> 4 | P7: =HYPERLINK(#REF!,"Link") -> #REF! | Q7: =HYPERLINK(#REF!,"Link") -> #REF!
A8: B08WRWPM22 | B8: boAt Micro USB 55 | C8: Accessories | D8: TVMounts,Stands&Turntables | E8: 499 | F8: 176.63 | G8: =E8*O8 -> 998 | H8: =F8*O8 -> 353.26 | I8: =(E8*K8)*O8 -> 648.7 | J8: =H8-G8 -> -644.74 | K8: 0.65 | L8: 4.1 | M8: 15188 | N8: Vivek kumar,Amazon | O8: =LEN(N8)-LEN(SUBSTITUTE(N8,",",""))+1 -> 2 | P8: =HYPERLINK(#REF!,"Link") -> #REF! | Q8: =HYPERLINK(#REF!,"Link") -> #REF!
A9: B08DDRGWTJ | B9: MI Usb Type-C Cable | C9: Accessories | D9: Cables | E9: 299 | F9: 229 | G9: =E9*O9 -> 299 | H9: =F9*O9 -> 229 | I9: =(E9*K9)*O9 -> 68.77 | J9: =H9-G9 -> -70 | K9: 0.23 | L9: 4.3 | M9: 30411 | N9: Pavan A | O9: =LEN(N9)-LEN(SUBSTITUTE(N9,",",""))+1 -> 1 | P9: =HYPERLINK(#REF!,"Link") -> #REF! | Q9: =HYPERLINK(#REF!,"Link") -> #REF!
A10: B008IFXQFU | B10: TP-Link USB WiFi Adapter | C10: Accessories | D10: SpeakerAccessories | E10: 999 | F10: 499 | G10: =E10*O10 -> 1998 | H10: =F10*O10 -> 998 | I10: =(E10*K10)*O10 -> 999 | J10: =H10-G10 -> -1000 | K10: 0.5 | L10: 4.2 | M10: 179691 | N10: Azhar JuMan,Anirudh | O10: =LEN(N10)-LEN(SUBSTITUTE(N10,",",""))+1 -> 2 | P10: =HYPERLINK(#REF!,"Link") -> #REF! | Q10: =HYPERLINK(#REF!,"Link") -> #REF!
A11: B082LZGK39 | B11: Ambrane Unbreakable 60W / | C11: Accessories | D11: Cables | E11: 299 | F11: 199 | G11: =E11*O11 -> 897 | H11: =F11*O11 -> 597 | I11: =(E11*K11)*O11 -> 296.01 | J11: =H11-G11 -> -300 | K11: 0.33 | L11: 4 | M11: 43994 | N11: ArdKn,Nirbhay kumar,Sagar | O11: =LEN(N11)-LEN(SUBSTITUTE(N11,",",""))+1 -> 3 | P11: =HYPERLINK(#REF!,"Link") -> #REF! | Q11: =HYPERLINK(#REF!,"Link") -> #REF!
A12: B08CF3D7QR | B12: Portronics Konnect L POR-1081 | C12: Projectors | E12: 339 | F12: 154 | G12: =E12*O12 -> 1356 | H12: =F12*O12 -> 616 | I12: =(E12*K12)*O12 -> 745.8 | J12: =H12-G12 -> -740 | K12: 0.55 | L12: 4.3 | M12: 13391 | N12: Tanya,Anu,Akshay,Vishal Sagara | O12: =LEN(N12)-LEN(SUBSTITUTE(N12,",",""))+1 -> 4 | P12: =HYPERLINK(#REF!,"Link") -> #REF! | Q12: =HYPERLINK(#REF!,"Link") -> #REF!
A13: B0789LZTCJ | B13: boAt Rugged v3 Extra | C13: Accessories | D13: Adapters | E13: 799 | F13: 299 | G13: =E13*O13 -> 3196 | H13: =F13*O13 -> 1196 | I13: =(E13*K13)*O13 -> 2013.48 | J13: =H13-G13 -> -2000 | K13: 0.63 | L13: 4.2 | M13: 94363 | N13: Omkar dhale,JD,HEMALATHA,Ajwadh | O13: =LEN(N13)-LEN(SUBSTITUTE(N13,",",""))+1 -> 4 | P13: =HYPERLINK(#REF!,"Link") -> #REF! | Q13: =HYPERLINK(#REF!,"Link") -> #REF!
A14: B07KSMBL2H | B14: AmazonBasics Flexible Premium HDMI | C14: SatelliteEquipment | D14: SatelliteReceivers | E14: 700 | F14: 219 | G14: =E14*O14 -> 1400 | H14: =F14*O14 -> 438 | I14: =(E14*K14)*O14 -> 966 | J14: =H14-G14 -> -962 | K14: 0.69 | L14: 4.4 | M14: 426973 | N14: Rishav Gossain,Shashank | O14: =LEN(N14)-LEN(SUBSTITUTE(N14,",",""))+1 -> 2 | P14: =HYPERLINK(#REF!,"Link") -> #REF! | Q14: =HYPERLINK(#REF!,"Link") -> #REF!
A15: B085DTN6R2 | B15: Portronics Konnect CL 20W | C15: Cables&Accessories | D15: Cables | E15: 899 | F15: 350 | G15: =E15*O15 -> 5394 | H15: =F15*O15 -> 2100 | I15: =(E15*K15)*O15 -> 3290.34 | J15: =H15-G15 -> -3294 | K15: 0.61 | L15: 4.2 | M15: 2262 | N15: Priya,Mansi,Plaban,Vivek,Taufique Ahmed,Praveen | O15: =LEN(N15)-LEN(SUBSTITUTE(N15,",",""))+1 -> 6 | P15: =HYPERLINK(#REF!,"Link") -> #REF! | Q15: =HYPERLINK(#REF!,"Link") -> #REF!
A16: B09KLVMZ3B | B16: Portronics Konnect L 1.2M | C16: Accessories | D16: Cables | E16: 399 | F16: 159 | G16: =E16*O16 -> 798 | H16: =F16*O16 -> 318 | I16: =(E16*K16)*O16 -> 478.8 | J16: =H16-G16 -> -480 | K16: 0.6 | L16: 4.1 | M16: 4768 | N16: Deepaak Singh,siva | O16: =LEN(N16)-LEN(SUBSTITUTE(N16,",",""))+1 -> 2 | P16: =HYPERLINK(#REF!,"Link") -> #REF! | Q16: =HYPERLINK(#REF!,"Link") -> #REF!
A17: B083342NKJ | B17: MI Braided USB Type-C | C17: MediaStreamingDevices | D17: StreamingClients | E17: 399 | F17: 349 | G17: =E17*O17 -> 399 | H17: =F17*O17 -> 349 | I17: =(E17*K17)*O17 -> 51.87 | J17: =H17-G17 -> -50 | K17: 0.13 | L17: 4.4 | M17: 18757 | N17: Birendra ku | O17: =LEN(N17)-LEN(SUBSTITUTE(N17,",",""))+1 -> 1 | P17: =HYPERLINK(#REF!,"Link") -> #REF! | Q17: =HYPERLINK(#REF!,"Link") -> #REF!
A18: B0B6F7LX4C | B18: MI 80 cm | C18: AVReceivers&Amplifiers | E18: 24999 | F18: 13999 | G18: =E18*O18 -> 49998 | H18: =F18*O18 -> 27998 | I18: =(E18*K18)*O18 -> 21999.12 | J18: =H18-G18 -> -22000 | K18: 0.44 | L18: 4.2 | M18: 32840 | N18: Manoj maddheshiya,Manoj | O18: =LEN(N18)-LEN(SUBSTITUTE(N18,",",""))+1 -> 2 | P18: =HYPERLINK(#REF!,"Link") -> #REF! | Q18: =HYPERLINK(#REF!,"Link") -> #REF!
A19: B082LSVT4B | B19: Ambrane Unbreakable 60W / | C19: Speakers | D19: TowerSpeakers | E19: 399 | F19: 249 | G19: =E19*O19 -> 1197 | H19: =F19*O19 -> 747 | I19: =(E19*K19)*O19 -> 454.86 | J19: =H19-G19 -> -450 | K19: 0.38 | L19: 4 | M19: 43994 | N19: ArdKn,Nirbhay kumar,Sagar | O19: =LEN(N19)-LEN(SUBSTITUTE(N19,",",""))+1 -> 3 | P19: =HYPERLINK(#REF!,"Link") -> #REF! | Q19: =HYPERLINK(#REF!,"Link") -> #REF!
A20: B08WRBG3XW | B20: boAt Type C A325 | C20: Accessories | D20: 3DGlasses | E20: 499 | F20: 199 | G20: =E20*O20 -> 998 | H20: =F20*O20 -> 398 | I20: =(E20*K20)*O20 -> 598.8 | J20: =H20-G20 -> -600 | K20: 0.6 | L20: 4.1 | M20: 13045 | N20: Rohan Narkar,JAGWINDER | O20: =LEN(N20)-LEN(SUBSTITUTE(N20,",",""))+1 -> 2 | P20: =HYPERLINK(#REF!,"Link") -> #REF! | Q20: =HYPERLINK(#REF!,"Link") -> #REF!
A21: B08DPLCM6T | B21: LG 80 cm | C21: SmartWatches | E21: 21990 | F21: 13490 | G21: =E21*O21 -> 65970 | H21: =F21*O21 -> 40470 | I21: =(E21*K21)*O21 -> 25728.3 | J21: =H21-G21 -> -25500 | K21: 0.39 | L21: 4.3 | M21: 11976 | N21: NIRMAL.N,Manoj kumar,SOMNATH | O21: =LEN(N21)-LEN(SUBSTITUTE(N21,",",""))+1 -> 3 | P21: =HYPERLINK(#REF!,"Link") -> #REF! | Q21: =HYPERLINK(#REF!,"Link") -> #REF!
A22: B09C6HXFC1 | B22: Duracell USB Lightning Apple | C22: MobileAccessories | D22: Chargers | E22: 1799 | F22: 970 | G22: =E22*O22 -> 3598 | H22: =F22*O22 -> 1940 | I22: =(E22*K22)*O22 -> 1655.08 | J22: =H22-G22 -> -1658 | K22: 0.46 | L22: 4.5 | M22: 815 | N22: Prasannavijayaraghavan G.,Preet | O22: =LEN(N22)-LEN(SUBSTITUTE(N22,",",""))+1 -> 2 | P22: =HYPERLINK(#REF!,"Link") -> #REF! | Q22: =HYPERLINK(#REF!,"Link") -> #REF!
A23: B085194JFL | B23: tizum HDMI to VGA | C23: Smartphones&BasicMobiles | D23: Smartphones | E23: 499 | F23: 279 | G23: =E23*O23 -> 1497 | H23: =F23*O23 -> 837 | I23: =(E23*K23)*O23 -> 658.68 | J23: =H23-G23 -> -660 | K23: 0.44 | L23: 3.7 | M23: 10962 | N23: aditya d.,Paranthaman,ashik | O23: =LEN(N23)-LEN(SUBSTITUTE(N23,",",""))+1 -> 3 | P23: =HYPERLINK(#REF!,"Link") -> #REF! | Q23: =HYPERLINK(#REF!,"Link") -> #REF!
A24: B09F6S8BT6 | B24: Samsung 80 cm | C24: MemoryCards | D24: MicroSD | E24: 22900 | F24: 13490 | G24: =E24*O24 -> 45800 | H24: =F24*O24 -> 26980 | I24: =(E24*K24)*O24 -> 18778 | J24: =H24-G24 -> -18820 | K24: 0.41 | L24: 4.3 | M24: 16299 | N24: Rahman Ali,MARIYA | O24: =LEN(N24)-LEN(SUBSTITUTE(N24,",",""))+1 -> 2 | P24: =HYPERLINK(#REF!,"Link") -> #REF! | Q24: =HYPERLINK(#REF!,"Link") -> #REF!
A25: B09NHVCHS9 | B25: Flix Micro Usb Cable | C25: Smartphones&BasicMobiles | D25: BasicMobiles | E25: 199 | F25: 59 | G25: =E25*O25 -> 597 | H25: =F25*O25 -> 177 | I25: =(E25*K25)*O25 -> 417.9 | J25: =H25-G25 -> -420 | K25: 0.7 | L25: 4 | M25: 9378 | N25: $@|\|TO$|-|,Sethu madhav,Akash | O25: =LEN(N25)-LEN(SUBSTITUTE(N25,",",""))+1 -> 3 | P25: =HYPERLINK(#REF!,"Link") -> #REF! | Q25: =HYPERLINK(#REF!,"Link") -> #REF!
A26: B0B1YVCJ2Y | B26: Acer 80 cm | C26: Headphones | D26: In-Ear | E26: 19990 | F26: 11499 | G26: =E26*O26 -> 99950 | H26: =F26*O26 -> 57495 | I26: =(E26*K26)*O26 -> 41979 | J26: =H26-G26 -> -42455 | K26: 0.42 | L26: 4.3 | M26: 4703 | N26: Ayush,ROHIT A.,Kedar,Haran,Santosh | O26: =LEN(N26)-LEN(SUBSTITUTE(N26,",",""))+1 -> 5 | P26: =HYPERLINK(#REF!,"Link") -> #REF! | Q26: =HYPERLINK(#REF!,"Link") -> #REF!
A27: B01M4GGIVU | B27: Tizum High Speed HDMI | C27: MobileAccessories | D27: Chargers | E27: 699 | F27: 199 | G27: =E27*O27 -> 2097 | H27: =F27*O27 -> 597 | I27: =(E27*K27)*O27 -> 1509.84 | J27: =H27-G27 -> -1500 | K27: 0.72 | L27: 4.2 | M27: 12153 | N27: Yashpreet Singh,Abiram,Aakaash | O27: =LEN(N27)-LEN(SUBSTITUTE(N27,",",""))+1 -> 3 | P27: =HYPERLINK(#REF!,"Link") -> #REF! | Q27: =HYPERLINK(#REF!,"Link") -> #REF!
A28: B08B42LWKN | B28: OnePlus 80 cm | C28: MobileAccessories | D28: AutomobileAccessories | E28: 19999 | F28: 14999 | G28: =E28*O28 -> 39998 | H28: =F28*O28 -> 29998 | I28: =(E28*K28)*O28 -> 9999.5 | J28: =H28-G28 -> -10000 | K28: 0.25 | L28: 4.2 | M28: 34899 | N28: ATHARVA BONDRE,Sujitkumar | O28: =LEN(N28)-LEN(SUBSTITUTE(N28,",",""))+1 -> 2 | P28: =HYPERLINK(#REF!,"Link") -> #REF! | Q28: =HYPERLINK(#REF!,"Link") -> #REF!
A29: B094JNXNPV | B29: Ambrane Unbreakable 3 in | C29: MobileAccessories | D29: Chargers | E29: 399 | F29: 299 | G29: =E29*O29 -> 1596 | H29: =F29*O29 -> 1196 | I29: =(E29*K29)*O29 -> 399 | J29: =H29-G29 -> -400 | K29: 0.25 | L29: 4 | M29: 2766 | N29: Anand sarma,lokeshnist,C,SAI | O29: =LEN(N29)-LEN(SUBSTITUTE(N29,",",""))+1 -> 4 | P29: =HYPERLINK(#REF!,"Link") -> #REF! | Q29: =HYPERLINK(#REF!,"Link") -> #REF!
A30: B09W5XR9RT | B30: Duracell USB C To | C30: MobileAccessories | D30: Cables&Adapters | E30: 1999 | F30: 970 | G30: =E30*O30 -> 3998 | H30: =F30*O30 -> 1940 | I30: =(E30*K30)*O30 -> 2038.98 | J30: =H30-G30 -> -2058 | K30: 0.51 | L30: 4.4 | M30: 184 | N30: Amazon Customer,Govind | O30: =LEN(N30)-LEN(SUBSTITUTE(N30,",",""))+1 -> 2 | P30: =HYPERLINK(#REF!,"Link") -> #REF! | Q30: =HYPERLINK(#REF!,"Link") -> #REF!
A31: B077Z65HSD | B31: boAt A400 USB Type-C | C31: MobileAccessories | D31: Photo&VideoAccessories | E31: 999 | F31: 299 | G31: =E31*O31 -> 2997 | H31: =F31*O31 -> 897 | I31: =(E31*K31)*O31 -> 2097.9 | J31: =H31-G31 -> -2100 | K31: 0.7 | L31: 4.3 | M31: 20850 | N31: GHOST,Amazon Customer,A | O31: =LEN(N31)-LEN(SUBSTITUTE(N31,",",""))+1 -> 3 | P31: =HYPERLINK(#REF!,"Link") -> #REF! | Q31: =HYPERLINK(#REF!,"Link") -> #REF!
A32: B00NH11PEY | B32: AmazonBasics USB 2.0 - | C32: MobileAccessories | D32: Photo&VideoAccessories | E32: 750 | F32: 199 | G32: =E32*O32 -> 6000 | H32: =F32*O32 -> 1592 | I32: =(E32*K32)*O32 -> 4380 | J32: =H32-G32 -> -4408 | K32: 0.73 | L32: 4.5 | M32: 74976 | N32: Pravin Kumar,Maestrov,rag,Mukundha2good,Amazon_Shopper,Sonic,Pratap,Amazon | O32: =LEN(N32)-LEN(SUBSTITUTE(N32,",",""))+1 -> 8 | P32: =HYPERLINK(#REF!,"Link") -> #REF! | Q32: =HYPERLINK(#REF!,"Link") -> #REF!
A33: B09CMM3VGK | B33: Ambrane 60W / 3A | C33: MobileAccessories | D33: Stands | E33: 499 | F33: 179 | G33: =E33*O33 -> 1497 | H33: =F33*O33 -> 537 | I33: =(E33*K33)*O33 -> 958.08 | J33: =H33-G33 -> -960 | K33: 0.64 | L33: 4 | M33: 1934 | N33: Rishabh,Amazon Customer,Darpan | O33: =LEN(N33)-LEN(SUBSTITUTE(N33,",",""))+1 -> 3 | P33: =HYPERLINK(#REF!,"Link") -> #REF! | Q33: =HYPERLINK(#REF!,"Link") -> #REF!
... A42: B00NH11KIK | B42: AmazonBasics USB 2.0 Cable | C42: LaptopAccessories | D42: CameraPrivacyCovers | E42: 695 | F42: 209 | G42: =E42*O42 -> 4865 | H42: =F42*O42 -> 1463 | I42: =(E42*K42)*O42 -> 3405.5 | J42: =H42-G42 -> -3402 | K42: 0.7 | L42: 4.5 | M42: 107687 | N42: Shiva,Uzef,kottala samuel,Renjith,Dhivakaran,Mark,Utkarsh | O42: =LEN(N42)-LEN(SUBSTITUTE(N42,",",""))+1 -> 7 | P42: =HYPERLINK(#REF!,"Link") -> #REF! | Q42: =HYPERLINK(#REF!,"Link") -> #REF!
A43: B09JPC82QC | B43: Mi 108 cm | C43: Adapters | E43: 34999 | F43: 19999 | G43: =E43*O43 -> 104997 | H43: =F43*O43 -> 59997 | I43: =(E43*K43)*O43 -> 45148.71 | J43: =H43-G43 -> -45000 | K43: 0.43 | L43: 4.3 | M43: 27151 | N43: Sameer Patil,TechnoLoon,Deepti | O43: =LEN(N43)-LEN(SUBSTITUTE(N43,",",""))+1 -> 3 | P43: =HYPERLINK(#REF!,"Link") -> #REF! | Q43: =HYPERLINK(#REF!,"Link") -> #REF!
A44: B07JW1Y6XV | B44: Wayona Nylon Braided 3A | C44: MobileAccessories | D44: DÃ©cor | E44: 1099 | F44: 399 | G44: =E44*O44 -> 4396 | H44: =F44*O44 -> 1596 | I44: =(E44*K44)*O44 -> 2813.44 | J44: =H44-G44 -> -2800 | K44: 0.64 | L44: 4.2 | M44: 24269 | N44: Manav,Adarsh gupta,Sundeep,S.Sayeed | O44: =LEN(N44)-LEN(SUBSTITUTE(N44,",",""))+1 -> 4 | P44: =HYPERLINK(#REF!,"Link") -> #REF! | Q44: =HYPERLINK(#REF!,"Link") -> #REF!
A45: B07KRCW6LZ | B45: TP-Link Nano AC600 USB | C45: MobileAccessories | D45: Mounts | E45: 1599 | F45: 999 | G45: =E45*O45 -> 3198 | H45: =F45*O45 -> 1998 | I45: =(E45*K45)*O45 -> 1215.24 | J45: =H45-G45 -> -1200 | K45: 0.38 | L45: 4.3 | M45: 12093 | N45: Paul Joe,Simon | O45: =LEN(N45)-LEN(SUBSTITUTE(N45,",",""))+1 -> 2 | P45: =HYPERLINK(#REF!,"Link") -> #REF! | Q45: =HYPERLINK(#REF!,"Link") -> #REF!
A46: B09NJN8L25 | B46: FLiX | C46: PenDrives | E46: 199 | F46: 59 | G46: =E46*O46 -> 597 | H46: =F46*O46 -> 177 | I46: =(E46*K46)*O46 -> 417.9 | J46: =H46-G46 -> -420 | K46: 0.7 | L46: 4 | M46: 9378 | N46: $@|\|TO$|-|,Sethu madhav,Akash | O46: =LEN(N46)-LEN(SUBSTITUTE(N46,",",""))+1 -> 3 | P46: =HYPERLINK(#REF!,"Link") -> #REF! | Q46: =HYPERLINK(#REF!,"Link") -> #REF!
A47: B07XJYYH7L | B47: Wecool Nylon Braided Multifunction | C47: Keyboards,Mice&InputDevices | D47: Mice | E47: 999 | F47: 333 | G47: =E47*O47 -> 3996 | H47: =F47*O47 -> 1332 | I47: =(E47*K47)*O47 -> 2677.32 | J47: =H47-G47 -> -2664 | K47: 0.67 | L47: 3.3 | M47: 9792 | N47: Amazon Customer,DHONDU,Saurabh,Promod | O47: =LEN(N47)-LEN(SUBSTITUTE(N47,",",""))+1 -> 4 | P47: =HYPERLINK(#REF!,"Link") -> #REF! | Q47: =HYPERLINK(#REF!,"Link") -> #REF!
A48: B002PD61Y4 | B48: D-Link DWA-131 300 Mbps | C48: Keyboards,Mice&InputDevices | D48: GraphicTablets | E48: 1208 | F48: 507 | G48: =E48*O48 -> 4832 | H48: =F48*O48 -> 2028 | I48: =(E48*K48)*O48 -> 2802.56 | J48: =H48-G48 -> -2804 | K48: 0.58 | L48: 4.1 | M48: 8131 | N48: nilesh,EAGLE,Manoj KNS,Titus | O48: =LEN(N48)-LEN(SUBSTITUTE(N48,",",""))+1 -> 4 | P48: =HYPERLINK(#REF!,"Link") -> #REF! | Q48: =HYPERLINK(#REF!,"Link") -> #REF!
A49: B014I8SSD0 | B49: Amazon Basics High-Speed HDMI | C49: LaptopAccessories | D49: Lapdesks | E49: 475 | F49: 309 | G49: =E49*O49 -> 950 | H49: =F49*O49 -> 618 | I49: =(E49*K49)*O49 -> 332.5 | J49: =H49-G49 -> -332 | K49: 0.35 | L49: 4.4 | M49: 426973 | N49: Rishav Gossain,Shashank | O49: =LEN(N49)-LEN(SUBSTITUTE(N49,",",""))+1 -> 2 | P49: =HYPERLINK(#REF!,"Link") -> #REF! | Q49: =HYPERLINK(#REF!,"Link") -> #REF!
A50: B09L8DSSFH | B50: 7SEVENÂ® Compatible for Samsung | C50: LaptopAccessories | D50: NotebookComputerStands | E50: 999 | F50: 399 | G50: =E50*O50 -> 2997 | H50: =F50*O50 -> 1197 | I50: =(E50*K50)*O50 -> 1798.2 | J50: =H50-G50 -> -1800 | K50: 0.6 | L50: 3.6 | M50: 493 | N50: MONTY,Qais Makani,Rajat | O50: =LEN(N50)-LEN(SUBSTITUTE(N50,",",""))+1 -> 3 | P50: =HYPERLINK(#REF!,"Link") -> #REF! | Q50: =HYPERLINK(#REF!,"Link") -> #REF!
A51: B07232M876 | B51: Amazonbasics Micro Usb Fast | C51: Keyboards,Mice&InputDevices | D51: Keyboards | E51: 395 | F51: 199 | G51: =E51*O51 -> 1975 | H51: =F51*O51 -> 995 | I51: =(E51*K51)*O51 -> 987.5 | J51: =H51-G51 -> -980 | K51: 0.5 | L51: 4.2 | M51: 92595 | N51: Neeraj Vishwakarma,Siddharth,SD1908,Mukundha2good,manjunath | O51: =LEN(N51)-LEN(SUBSTITUTE(N51,",",""))+1 -> 5 | P51: =HYPERLINK(#REF!,"Link") -> #REF! | Q51: =HYPERLINK(#REF!,"Link") -> #REF!
A52: B07P681N66 | B52: TP-Link AC600 600 Mbps | C52: Condenser | E52: 2199 | F52: 1199 | G52: =E52*O52 -> 6597 | H52: =F52*O52 -> 3597 | I52: =(E52*K52)*O52 -> 2968.65 | J52: =H52-G52 -> -3000 | K52: 0.45 | L52: 4.4 | M52: 24780 | N52: Anonymous,Sugam Agrawal,Diganta | O52: =LEN(N52)-LEN(SUBSTITUTE(N52,",",""))+1 -> 3 | P52: =HYPERLINK(#REF!,"Link") -> #REF! | Q52: =HYPERLINK(#REF!,"Link") -> #REF!
A53: B0711PVX6Z | B53: AmazonBasics Micro USB Fast | C53: DisposableBatteries | E53: 500 | F53: 179 | G53: =E53*O53 -> 2500 | H53: =F53*O53 -> 895 | I53: =(E53*K53)*O53 -> 1600 | J53: =H53-G53 -> -1605 | K53: 0.64 | L53: 4.2 | M53: 92595 | N53: Neeraj Vishwakarma,Siddharth,SD1908,Mukundha2good,manjunath | O53: =LEN(N53)-LEN(SUBSTITUTE(N53,",",""))+1 -> 5 | P53: =HYPERLINK(#REF!,"Link") -> #REF! | Q53: =HYPERLINK(#REF!,"Link") -> #REF!
A54: B082T6V3DT | B54: AmazonBasics New Release Nylon | C54: Paper | D54: Stationery | E54: 2100 | F54: 799 | G54: =E54*O54 -> 6300 | H54: =F54*O54 -> 2397 | I54: =(E54*K54)*O54 -> 3906 | J54: =H54-G54 -> -3903 | K54: 0.62 | L54: 4.3 | M54: 8188 | N54: Arun verma,Arv,Aashna | O54: =LEN(N54)-LEN(SUBSTITUTE(N54,",",""))+1 -> 3 | P54: =HYPERLINK(#REF!,"Link") -> #REF! | Q54: =HYPERLINK(#REF!,"Link") -> #REF!
A55: B07MKFNHKG | B55: VW 80 cm | C55: Scrapbooking | D55: Tape | E55: 12999 | F55: 6999 | G55: =E55*O55 -> 38997 | H55: =F55*O55 -> 20997 | I55: =(E55*K55)*O55 -> 17938.62 | J55: =H55-G55 -> -18000 | K55: 0.46 | L55: 4.2 | M55: 4003 | N55: Amazon Customer,Yousuf,Raja | O55: =LEN(N55)-LEN(SUBSTITUTE(N55,",",""))+1 -> 3 | P55: =HYPERLINK(#REF!,"Link") -> #REF! | Q55: =HYPERLINK(#REF!,"Link") -> #REF!
A56: B0BFWGBX61 | B56: Ambrane Unbreakable 3A Fast | C56: Keyboards,Mice&InputDevices | D56: Keyboard&MouseSets | E56: 349 | F56: 199 | G56: =E56*O56 -> 698 | H56: =F56*O56 -> 398 | I56: =(E56*K56)*O56 -> 300.14 | J56: =H56-G56 -> -300 | K56: 0.43 | L56: 4.1 | M56: 314 | N56: Vipan Agnihotri,Hitender | O56: =LEN(N56)-LEN(SUBSTITUTE(N56,",",""))+1 -> 2 | P56: =HYPERLINK(#REF!,"Link") -> #REF! | Q56: =HYPERLINK(#REF!,"Link") -> #REF!
A57: B01N90RZ4M | B57: Tata Sky Universal Remote | C57: ExternalHardDisks | E57: 499 | F57: 230 | G57: =E57*O57 -> 1996 | H57: =F57*O57 -> 920 | I57: =(E57*K57)*O57 -> 1077.84 | J57: =H57-G57 -> -1076 | K57: 0.54 | L57: 3.7 | M57: 2960 | N57: Jacob.,Dinesh Ahuja,Ashith,Pravin | O57: =LEN(N57)-LEN(SUBSTITUTE(N57,",",""))+1 -> 4 | P57: =HYPERLINK(#REF!,"Link") -> #REF! | Q57: =HYPERLINK(#REF!,"Link") -> #REF!
A58: B0088TKTY2 | B58: TP-LINK WiFi Dongle 300 | C58: VideoCameras | E58: 1399 | F58: 649 | G58: =E58*O58 -> 2798 | H58: =F58*O58 -> 1298 | I58: =(E58*K58)*O58 -> 1510.92 | J58: =H58-G58 -> -1500 | K58: 0.54 | L58: 4.2 | M58: 179691 | N58: Azhar JuMan,Anirudh | O58: =LEN(N58)-LEN(SUBSTITUTE(N58,",",""))+1 -> 2 | P58: =HYPERLINK(#REF!,"Link") -> #REF! | Q58: =HYPERLINK(#REF!,"Link") -> #REF!
A59: B09Q5SWVBJ | B59: OnePlus 80 cm | C59: Accessories | D59: Tripods&Monopods | E59: 21999 | F59: 15999 | G59: =E59*O59 -> 43998 | H59: =F59*O59 -> 31998 | I59: =(E59*K59)*O59 -> 11879.46 | J59: =H59-G59 -> -12000 | K59: 0.27 | L59: 4.2 | M59: 34899 | N59: ATHARVA BONDRE,Sujitkumar | O59: =LEN(N59)-LEN(SUBSTITUTE(N59,",",""))+1 -> 2 | P59: =HYPERLINK(#REF!,"Link") -> #REF! | Q59: =HYPERLINK(#REF!,"Link") -> #REF!
A60: B0B4DT8MKT | B60: Wecool Unbreakable 3 in | C60: Calculators | D60: Scientific | E60: 1499 | F60: 348 | G60: =E60*O60 -> 2998 | H60: =F60*O60 -> 696 | I60: =(E60*K60)*O60 -> 2308.46 | J60: =H60-G60 -> -2302 | K60: 0.77 | L60: 4.2 | M60: 656 | N60: nisar,Pralipta Kumar | O60: =LEN(N60)-LEN(SUBSTITUTE(N60,",",""))+1 -> 2 | P60: =HYPERLINK(#REF!,"Link") -> #REF! | Q60: =HYPERLINK(#REF!,"Link") -> #REF!
A61: B08CDKQ8T6 | B61: Portronics Konnect L 1.2Mtr, | C61: Repeaters&Extenders | E61: 349 | F61: 154 | G61: =E61*O61 -> 698 | H61: =F61*O61 -> 308 | I61: =(E61*K61)*O61 -> 390.88 | J61: =H61-G61 -> -390 | K61: 0.56 | L61: 4.3 | M61: 7064 | N61: Arun S.,Jeevan | O61: =LEN(N61)-LEN(SUBSTITUTE(N61,",",""))+1 -> 2 | P61: =HYPERLINK(#REF!,"Link") -> #REF! | Q61: =HYPERLINK(#REF!,"Link") -> #REF!
A62: B07B275VN9 | B62: Airtel DigitalTV DTH Television, | C62: Accessories | D62: Tripods&Monopods | E62: 799 | F62: 179 | G62: =E62*O62 -> 2397 | H62: =F62*O62 -> 537 | I62: =(E62*K62)*O62 -> 1869.66 | J62: =H62-G62 -> -1860 | K62: 0.78 | L62: 3.7 | M62: 2201 | N62: Periyasamy,Madhusudhanan,S Salman | O62: =LEN(N62)-LEN(SUBSTITUTE(N62,",",""))+1 -> 3 | P62: =HYPERLINK(#REF!,"Link") -> #REF! | Q62: =HYPERLINK(#REF!,"Link") -> #REF!
A63: B0B15CPR37 | B63: Samsung 108 cm | C63: Inks,Toners&Cartridges | D63: InkjetInkCartridges | E63: 47900 | F63: 32990 | G63: =E63*O63 -> 335300 | H63: =F63*O63 -> 230930 | I63: =(E63*K63)*O63 -> 103943 | J63: =H63-G63 -> -104370 | K63: 0.31 | L63: 4.3 | M63: 7109 | N63: Binu,Sabjan,Ramkapil,User,Amazon Customer,ganesh,basavaraj | O63: =LEN(N63)-LEN(SUBSTITUTE(N63,",",""))+1 -> 7 | P63: =HYPERLINK(#REF!,"Link") -> #REF! | Q63: =HYPERLINK(#REF!,"Link") -> #REF!
A64: B0994GFWBH | B64: Lapster 1.5 mtr USB | C64: Keyboards,Mice&InputDevices | D64: Keyboard&MiceAccessories | E64: 999 | F64: 139 | G64: =E64*O64 -> 2997 | H64: =F64*O64 -> 417 | I64: =(E64*K64)*O64 -> 2577.42 | J64: =H64-G64 -> -2580 | K64: 0.86 | L64: 4 | M64: 1313 | N64: pruthvi natraj,Phani,Amazon | O64: =LEN(N64)-LEN(SUBSTITUTE(N64,",",""))+1 -> 3 | P64: =HYPERLINK(#REF!,"Link") -> #REF! | Q64: =HYPERLINK(#REF!,"Link") -> #REF!
A65: B01GGKZ0V6 | B65: AmazonBasics USB Type-C to | C65: PCGamingPeripherals | D65: GamingMice | E65: 845 | F65: 329 | G65: =E65*O65 -> 1690 | H65: =F65*O65 -> 658 | I65: =(E65*K65)*O65 -> 1030.9 | J65: =H65-G65 -> -1032 | K65: 0.61 | L65: 4.2 | M65: 29746 | N65: harpreet,Y Kiran | O65: =LEN(N65)-LEN(SUBSTITUTE(N65,",",""))+1 -> 2 | P65: =HYPERLINK(#REF!,"Link") -> #REF! | Q65: =HYPERLINK(#REF!,"Link") -> #REF!
A66: B09F9YQQ7B | B66: Redmi 80 cm | C66: PaintingMaterials | D66: Paints | E66: 24999 | F66: 13999 | G66: =E66*O66 -> 74997 | H66: =F66*O66 -> 41997 | I66: =(E66*K66)*O66 -> 32998.68 | J66: =H66-G66 -> -33000 | K66: 0.44 | L66: 4.2 | M66: 45238 | N66: prateeq,Suraj Chand,viswanath | O66: =LEN(N66)-LEN(SUBSTITUTE(N66,",",""))+1 -> 3 | P66: =HYPERLINK(#REF!,"Link") -> #REF! | Q66: =HYPERLINK(#REF!,"Link") -> #REF!
A67: B014I8SX4Y | B67: Amazon Basics High-Speed HDMI | C67: Keyboards,Mice&InputDevices | D67: Keyboard&MiceAccessories | E67: 1400 | F67: 309 | G67: =E67*O67 -> 2800 | H67: =F67*O67 -> 618 | I67: =(E67*K67)*O67 -> 2184 | J67: =H67-G67 -> -2182 | K67: 0.78 | L67: 4.4 | M67: 426973 | N67: Rishav Gossain,Shashank | O67: =LEN(N67)-LEN(SUBSTITUTE(N67,",",""))+1 -> 2 | P67: =HYPERLINK(#REF!,"Link") -> #REF! | Q67: =HYPERLINK(#REF!,"Link") -> #REF!
A68: B09Q8HMKZX | B68: Portronics Konnect L 20W | C68: HardDiskBags | E68: 699 | F68: 263 | G68: =E68*O68 -> 2796 | H68: =F68*O68 -> 1052 | I68: =(E68*K68)*O68 -> 1733.52 | J68: =H68-G68 -> -1744 | K68: 0.62 | L68: 4.1 | M68: 450 | N68: Thenmozhi,manish,Brajesh Jha,sushil | O68: =LEN(N68)-LEN(SUBSTITUTE(N68,",",""))+1 -> 4 | P68: =HYPERLINK(#REF!,"Link") -> #REF! | Q68: =HYPERLINK(#REF!,"Link") -> #REF!
A69: B0B9XN9S3W | B69: Acer 80 cm | C69: Flashes | D69: Macro&RinglightFlashes | E69: 14990 | F69: 7999 | G69: =E69*O69 -> 14990 | H69: =F69*O69 -> 7999 | I69: =(E69*K69)*O69 -> 7045.3 | J69: =H69-G69 -> -6991 | K69: 0.47 | L69: 4.3 | M69: 457 | N69: ARUN KUMAR | O69: =LEN(N69)-LEN(SUBSTITUTE(N69,",",""))+1 -> 1 | P69: =HYPERLINK(#REF!,"Link") -> #REF! | Q69: =HYPERLINK(#REF!,"Link") -> #REF!
A70: B07966M8XH | B70: Model-P4 6 Way Swivel | E70: 2999 | F70: 1599 | G70: =E70*O70 -> 5998 | H70: =F70*O70 -> 3198 | I70: =(E70*K70)*O70 -> 2819.06 | J70: =H70-G70 -> -2800 | K70: 0.47 | L70: 4.2 | M70: 2727 | N70: Prashant Pradhan,Raghavendra | O70: =LEN(N70)-LEN(SUBSTITUTE(N70,",",""))+1 -> 2 | P70: =HYPERLINK(#REF!,"Link") -> #REF! | Q70: =HYPERLINK(#REF!,"Link") -> #REF!
A71: B01GGKYKQM | B71: Amazon Basics USB Type-C | C71: Routers | E71: 700 | F71: 219 | G71: =E71*O71 -> 5600 | H71: =F71*O71 -> 1752 | I71: =(E71*K71)*O71 -> 3864 | J71: =H71-G71 -> -3848 | K71: 0.69 | L71: 4.3 | M71: 20053 | N71: Hremant,Anjaneyulu,Madhav,NOTTADRIS,Deepak,P,M.SASIKUMAR,S.Suresh | O71: =LEN(N71)-LEN(SUBSTITUTE(N71,",",""))+1 -> 8 | P71: =HYPERLINK(#REF!,"Link") -> #REF! | Q71: =HYPERLINK(#REF!,"Link") -> #REF!
A72: B0B86CDHL1 | B72: oraimo 65W Type C | C72: Headphones | D72: Over-Ear | E72: 899 | F72: 349 | G72: =E72*O72 -> 1798 | H72: =F72*O72 -> 698 | I72: =(E72*K72)*O72 -> 1096.78 | J72: =H72-G72 -> -1100 | K72: 0.61 | L72: 4.5 | M72: 149 | N72: Ravi Shankar,Prakash | O72: =LEN(N72)-LEN(SUBSTITUTE(N72,",",""))+1 -> 2 | P72: =HYPERLINK(#REF!,"Link") -> #REF! | Q72: =HYPERLINK(#REF!,"Link") -> #REF!
A73: B0B5ZF3NRK | B73: CEDO 65W OnePlus Dash | C73: Speakers | D73: BluetoothSpeakers | E73: 599 | F73: 349 | G73: =E73*O73 -> 2396 | H73: =F73*O73 -> 1396 | I73: =(E73*K73)*O73 -> 1006.32 | J73: =H73-G73 -> -1000 | K73: 0.42 | L73: 4.1 | M73: 210 | N73: Satyanarayana,mohd irfan,Pankaj,Shirish | O73: =LEN(N73)-LEN(SUBSTITUTE(N73,",",""))+1 -> 4 | P73: =HYPERLINK(#REF!,"Link") -> #REF! | Q73: =HYPERLINK(#REF!,"Link") -> #REF!
A74: B09RFC46VP | B74: Redmi 108 cm | E74: 42999 | F74: 26999 | G74: =E74*O74 -> 128997 | H74: =F74*O74 -> 80997 | I74: =(E74*K74)*O74 -> 47728.89 | J74: =H74-G74 -> -48000 | K74: 0.37 | L74: 4.2 | M74: 45238 | N74: prateeq,Suraj Chand,viswanath | O74: =LEN(N74)-LEN(SUBSTITUTE(N74,",",""))+1 -> 3 | P74: =HYPERLINK(#REF!,"Link") -> #REF! | Q74: =HYPERLINK(#REF!,"Link") -> #REF!
A75: B08R69VDHT | B75: Pinnaclz Original Combo of | C75: Paper | D75: Stationery | E75: 499 | F75: 115 | G75: =E75*O75 -> 499 | H75: =F75*O75 -> 115 | I75: =(E75*K75)*O75 -> 384.23 | J75: =H75-G75 -> -384 | K75: 0.77 | L75: 4 | M75: 7732 | N75: Vijayan C | O75: =LEN(N75)-LEN(SUBSTITUTE(N75,",",""))+1 -> 1 | P75: =HYPERLINK(#REF!,"Link") -> #REF! | Q75: =HYPERLINK(#REF!,"Link") -> #REF!
A76: B09RWZRCP1 | B76: boAt Type C A750 | C76: RechargeableBatteries | E76: 999 | F76: 399 | G76: =E76*O76 -> 1998 | H76: =F76*O76 -> 798 | I76: =(E76*K76)*O76 -> 1198.8 | J76: =H76-G76 -> -1200 | K76: 0.6 | L76: 4.1 | M76: 1780 | N76: livin sebi,Anand | O76: =LEN(N76)-LEN(SUBSTITUTE(N76,",",""))+1 -> 2 | P76: =HYPERLINK(#REF!,"Link") -> #REF! | Q76: =HYPERLINK(#REF!,"Link") -> #REF!
A77: B09CMP1SC8 | B77: Ambrane 2 in 1 | C77: NetworkAdapters | D77: BluetoothAdapters | E77: 499 | F77: 199 | G77: =E77*O77 -> 499 | H77: =F77*O77 -> 199 | I77: =(E77*K77)*O77 -> 299.4 | J77: =H77-G77 -> -300 | K77: 0.6 | L77: 4.1 | M77: 602 | N77: Gopal krishna | O77: =LEN(N77)-LEN(SUBSTITUTE(N77,",",""))+1 -> 1 | P77: =HYPERLINK(#REF!,"Link") -> #REF! | Q77: =HYPERLINK(#REF!,"Link") -> #REF!
A78: B09YLXYP7Y | B78: Ambrane 60W / 3A | C78: Adapters | D78: USBtoUSBAdapters | E78: 399 | F78: 179 | G78: =E78*O78 -> 798 | H78: =F78*O78 -> 358 | I78: =(E78*K78)*O78 -> 438.9 | J78: =H78-G78 -> -440 | K78: 0.55 | L78: 4 | M78: 1423 | N78: Actual user,Shanti | O78: =LEN(N78)-LEN(SUBSTITUTE(N78,",",""))+1 -> 2 | P78: =HYPERLINK(#REF!,"Link") -> #REF! | Q78: =HYPERLINK(#REF!,"Link") -> #REF!
A79: B09ZPM4C2C | B79: TCL 80 cm | C79: Accessories | D79: Tripods&Monopods | E79: 30990 | F79: 10901 | G79: =E79*O79 -> 30990 | H79: =F79*O79 -> 10901 | I79: =(E79*K79)*O79 -> 20143.5 | J79: =H79-G79 -> -20089 | K79: 0.65 | L79: 4.1 | M79: 398 | N79: Nilesh K | O79: =LEN(N79)-LEN(SUBSTITUTE(N79,",",""))+1 -> 1 | P79: =HYPERLINK(#REF!,"Link") -> #REF! | Q79: =HYPERLINK(#REF!,"Link") -> #REF!
A80: B0B2DJDCPX | B80: SWAPKART Fast Charging Cable | C80: Accessories | D80: Film | E80: 499 | F80: 209 | G80: =E80*O80 -> 1497 | H80: =F80*O80 -> 627 | I80: =(E80*K80)*O80 -> 868.26 | J80: =H80-G80 -> -870 | K80: 0.58 | L80: 3.9 | M80: 536 | N80: Vinay,Amazon Customer,Naveenkumar | O80: =LEN(N80)-LEN(SUBSTITUTE(N80,",",""))+1 -> 3 | P80: =HYPERLINK(#REF!,"Link") -> #REF! | Q80: =HYPERLINK(#REF!,"Link") -> #REF!
A81: B0BCZCQTJX | B81: Firestick Remote | E81: 3999 | F81: 1434 | G81: =E81*O81 -> 3999 | H81: =F81*O81 -> 1434 | I81: =(E81*K81)*O81 -> 2559.36 | J81: =H81-G81 -> -2565 | K81: 0.64 | L81: 4 | M81: 32 | N81: Dharminder Singh | O81: =LEN(N81)-LEN(SUBSTITUTE(N81,",",""))+1 -> 1 | P81: =HYPERLINK(#REF!,"Link") -> #REF! | Q81: =HYPERLINK(#REF!,"Link") -> #REF!
A82: B07LGT55SJ | B82: Wayona Usb Nylon Braided | C82: USBGadgets | D82: Lamps | E82: 1099 | F82: 399 | G82: =E82*O82 -> 4396 | H82: =F82*O82 -> 1596 | I82: =(E82*K82)*O82 -> 2813.44 | J82: =H82-G82 -> -2800 | K82: 0.64 | L82: 4.2 | M82: 24269 | N82: Manav,Adarsh gupta,Sundeep,S.Sayeed | O82: =LEN(N82)-LEN(SUBSTITUTE(N82,",",""))+1 -> 4 | P82: =HYPERLINK(#REF!,"Link") -> #REF! | Q82: =HYPERLINK(#REF!,"Link") -> #REF!
A83: B09NKZXMWJ | B83: Flix | C83: Accessories | D83: Cleaners | E83: 249 | F83: 139 | G83: =E83*O83 -> 747 | H83: =F83*O83 -> 417 | I83: =(E83*K83)*O83 -> 328.68 | J83: =H83-G83 -> -330 | K83: 0.44 | L83: 4 | M83: 9378 | N83: $@|\|TO$|-|,Sethu madhav,Akash | O83: =LEN(N83)-LEN(SUBSTITUTE(N83,",",""))+1 -> 3 | P83: =HYPERLINK(#REF!,"Link") -> #REF! | Q83: =HYPERLINK(#REF!,"Link") -> #REF!
A84: B08QX1CC14 | B84: SKYWALL 81.28 cm | C84: SecurityCameras | D84: DomeCameras | E84: 19125 | F84: 7299 | G84: =E84*O84 -> 38250 | H84: =F84*O84 -> 14598 | I84: =(E84*K84)*O84 -> 23715 | J84: =H84-G84 -> -23652 | K84: 0.62 | L84: 3.4 | M84: 902 | N84: Naresh Patel,Bhaskar | O84: =LEN(N84)-LEN(SUBSTITUTE(N84,",",""))+1 -> 2 | P84: =HYPERLINK(#REF!,"Link") -> #REF! | Q84: =HYPERLINK(#REF!,"Link") -> #REF!
A85: B0974H97TJ | B85: boAt A 350 Type | C85: TabletAccessories | D85: ScreenProtectors | E85: 799 | F85: 299 | G85: =E85*O85 -> 5593 | H85: =F85*O85 -> 2093 | I85: =(E85*K85)*O85 -> 3523.59 | J85: =H85-G85 -> -3500 | K85: 0.63 | L85: 4.4 | M85: 28791 | N85: ð•µð–†ð–™ð–Žð–“ ð•®ð–ð–†ð–‰ð–ð–†,palpandia153,Arvind,Nithyadhakshina,Basha_Neerati,shaker,Amazon | O85: =LEN(N85)-LEN(SUBSTITUTE(N85,",",""))+1 -> 7 | P85: =HYPERLINK(#REF!,"Link") -> #REF! | Q85: =HYPERLINK(#REF!,"Link") -> #REF!
A86: B07GVGTSLN | B86: Wayona Usb Type C | C86: PCGamingPeripherals | D86: Gamepads | E86: 1299 | F86: 325 | G86: =E86*O86 -> 2598 | H86: =F86*O86 -> 650 | I86: =(E86*K86)*O86 -> 1948.5 | J86: =H86-G86 -> -1948 | K86: 0.75 | L86: 4.2 | M86: 10576 | N86: Sunil Funde,Biju | O86: =LEN(N86)-LEN(SUBSTITUTE(N86,",",""))+1 -> 2 | P86: =HYPERLINK(#REF!,"Link") -> #REF! | Q86: =HYPERLINK(#REF!,"Link") -> #REF!
A87: B09VCHLSJF | B87: OnePlus 108 cm | C87: Calculators | D87: Basic | E87: 39999 | F87: 29999 | G87: =E87*O87 -> 79998 | H87: =F87*O87 -> 59998 | I87: =(E87*K87)*O87 -> 19999.5 | J87: =H87-G87 -> -20000 | K87: 0.25 | L87: 4.2 | M87: 7298 | N87: Abhishek Kumar,Arun | O87: =LEN(N87)-LEN(SUBSTITUTE(N87,",",""))+1 -> 2 | P87: =HYPERLINK(#REF!,"Link") -> #REF! | Q87: =HYPERLINK(#REF!,"Link") -> #REF!
A88: B0B1YZX72F | B88: Acer 127 cm | C88: USBHubs | E88: 40990 | F88: 27999 | G88: =E88*O88 -> 204950 | H88: =F88*O88 -> 139995 | I88: =(E88*K88)*O88 -> 65584 | J88: =H88-G88 -> -64955 | K88: 0.32 | L88: 4.3 | M88: 4703 | N88: Ayush,ROHIT A.,Kedar,Haran,Santosh | O88: =LEN(N88)-LEN(SUBSTITUTE(N88,",",""))+1 -> 5 | P88: =HYPERLINK(#REF!,"Link") -> #REF! | Q88: =HYPERLINK(#REF!,"Link") -> #REF!
A89: B092BJMT8Q | B89: Samsung 108 cm | C89: Audio&VideoAccessories | D89: PCMicrophones | E89: 52900 | F89: 30990 | G89: =E89*O89 -> 370300 | H89: =F89*O89 -> 216930 | I89: =(E89*K89)*O89 -> 151823 | J89: =H89-G89 -> -153370 | K89: 0.41 | L89: 4.3 | M89: 7109 | N89: Binu,Sabjan,Ramkapil,User,Amazon Customer,ganesh,basavaraj | O89: =LEN(N89)-LEN(SUBSTITUTE(N89,",",""))+1 -> 7 | P89: =HYPERLINK(#REF!,"Link") -> #REF! | Q89: =HYPERLINK(#REF!,"Link") -> #REF!
A90: B0BMXMLSMM | B90: Lapster 65W compatible for | C90: Speakers | D90: OutdoorSpeakers | E90: 999 | F90: 199 | G90: =E90*O90 -> 3996 | H90: =F90*O90 -> 796 | I90: =(E90*K90)*O90 -> 3196.8 | J90: =H90-G90 -> -3200 | K90: 0.8 | L90: 4.5 | M90: 127 | N90: Nadhiyarasan,Saurabh Aggarwal,Dibya,Sai | O90: =LEN(N90)-LEN(SUBSTITUTE(N90,",",""))+1 -> 4 | P90: =HYPERLINK(#REF!,"Link") -> #REF! | Q90: =HYPERLINK(#REF!,"Link") -> #REF!
A91: B07JH1C41D | B91: Wayona Nylon Braided | C91: LaptopAccessories | D91: Bags&Sleeves | E91: 1999 | F91: 649 | G91: =E91*O91 -> 7996 | H91: =F91*O91 -> 2596 | I91: =(E91*K91)*O91 -> 5437.28 | J91: =H91-G91 -> -5400 | K91: 0.68 | L91: 4.2 | M91: 24269 | N91: Manav,Adarsh gupta,Sundeep,S.Sayeed | O91: =LEN(N91)-LEN(SUBSTITUTE(N91,",",""))+1 -> 4 | P91: =HYPERLINK(#REF!,"Link") -> #REF! | Q91: =HYPERLINK(#REF!,"Link") -> #REF!
A92: B0141EZMAI | B92: Gizga Essentials USB WiFi | C92: ExternalMemoryCardReaders | E92: 800 | F92: 269 | G92: =E92*O92 -> 3200 | H92: =F92*O92 -> 1076 | I92: =(E92*K92)*O92 -> 2112 | J92: =H92-G92 -> -2124 | K92: 0.66 | L92: 3.6 | M92: 10134 | N92: SQL,ARUN KUMAR,veer,Ravi | O92: =LEN(N92)-LEN(SUBSTITUTE(N92,",",""))+1 -> 4 | P92: =HYPERLINK(#REF!,"Link") -> #REF! | Q92: =HYPERLINK(#REF!,"Link") -> #REF!
A93: B09Q5P2MT3 | B93: OnePlus 108 cm | C93: Cables&Accessories | D93: Cables | E93: 31999 | F93: 24999 | G93: =E93*O93 -> 63998 | H93: =F93*O93 -> 49998 | I93: =(E93*K93)*O93 -> 14079.56 | J93: =H93-G93 -> -14000 | K93: 0.22 | L93: 4.2 | M93: 34899 | N93: ATHARVA BONDRE,Sujitkumar | O93: =LEN(N93)-LEN(SUBSTITUTE(N93,",",""))+1 -> 2 | P93: =HYPERLINK(#REF!,"Link") -> #REF! | Q93: =HYPERLINK(#REF!,"Link") -> #REF!
A94: B08HDH26JX | B94: boAt Deuce USB 300 | C94: Memory | E94: 699 | F94: 299 | G94: =E94*O94 -> 2796 | H94: =F94*O94 -> 1196 | I94: =(E94*K94)*O94 -> 1593.72 | J94: =H94-G94 -> -1600 | K94: 0.57 | L94: 4.2 | M94: 94363 | N94: Omkar dhale,JD,HEMALATHA,Ajwadh | O94: =LEN(N94)-LEN(SUBSTITUTE(N94,",",""))+1 -> 4 | P94: =HYPERLINK(#REF!,"Link") -> #REF! | Q94: =HYPERLINK(#REF!,"Link") -> #REF!
A95: B09VT6JKRP | B95: Lapster USB 3.0 A | C95: UninterruptedPowerSupplies | E95: 999 | F95: 199 | G95: =E95*O95 -> 4995 | H95: =F95*O95 -> 995 | I95: =(E95*K95)*O95 -> 3996 | J95: =H95-G95 -> -4000 | K95: 0.8 | L95: 4.1 | M95: 425 | N95: Vivek Ramachandran,Pavan,Rahul,Push,Yuthika | O95: =LEN(N95)-LEN(SUBSTITUTE(N95,",",""))+1 -> 5 | P95: =HYPERLINK(#REF!,"Link") -> #REF! | Q95: =HYPERLINK(#REF!,"Link") -> #REF!
A96: B09T3KB6JZ | B96: TCL 100 cm | C96: Cases | E96: 40990 | F96: 18990 | G96: =E96*O96 -> 40990 | H96: =F96*O96 -> 18990 | I96: =(E96*K96)*O96 -> 22134.6 | J96: =H96-G96 -> -22000 | K96: 0.54 | L96: 4.2 | M96: 6659 | N96: KIRAN BABU | O96: =LEN(N96)-LEN(SUBSTITUTE(N96,",",""))+1 -> 1 | P96: =HYPERLINK(#REF!,"Link") -> #REF! | Q96: =HYPERLINK(#REF!,"Link") -> #REF!
A97: B093QCY6YJ | B97: ZEBRONICS ZEB-USB150WF1 WiFi USB | C97: MemoryCards | D97: SecureDigitalCards | E97: 349 | F97: 290 | G97: =E97*O97 -> 1047 | H97: =F97*O97 -> 870 | I97: =(E97*K97)*O97 -> 177.99 | J97: =H97-G97 -> -177 | K97: 0.17 | L97: 3.7 | M97: 1977 | N97: Mohseen Qureshi,Karan,Pranav | O97: =LEN(N97)-LEN(SUBSTITUTE(N97,",",""))+1 -> 3 | P97: =HYPERLINK(#REF!,"Link") -> #REF! | Q97: =HYPERLINK(#REF!,"Link") -> #REF!
A98: B093ZNQZ2Y | B98: LOHAYA Remote Compatible for | C98: MobileAccessories | D98: Photo&VideoAccessories | E98: 799 | F98: 249 | G98: =E98*O98 -> 2397 | H98: =F98*O98 -> 747 | I98: =(E98*K98)*O98 -> 1653.93 | J98: =H98-G98 -> -1650 | K98: 0.69 | L98: 3.8 | M98: 1079 | N98: mohamednathar,Amazon Customer,Ashwini | O98: =LEN(N98)-LEN(SUBSTITUTE(N98,",",""))+1 -> 3 | P98: =HYPERLINK(#REF!,"Link") -> #REF! | Q98: =HYPERLINK(#REF!,"Link") -> #REF!
A99: B08LKS3LSP | B99: Gilary Multi Charging Cable, | C99: Audio&VideoAccessories | D99: Webcams&VoIPEquipment | E99: 999 | F99: 345 | G99: =E99*O99 -> 2997 | H99: =F99*O99 -> 1035 | I99: =(E99*K99)*O99 -> 1948.05 | J99: =H99-G99 -> -1962 | K99: 0.65 | L99: 3.7 | M99: 1097 | N99: kishore movva,Nithya,Balaji | O99: =LEN(N99)-LEN(SUBSTITUTE(N99,",",""))+1 -> 3 | P99: =HYPERLINK(#REF!,"Link") -> #REF! | Q99: =HYPERLINK(#REF!,"Link") -> #REF!
A100: B00V4BGDKU | B100: TP-Link UE300 USB 3.0 | C100: LaptopAccessories | D100: CoolingPads | E100: 1899 | F100: 1099 | G100: =E100*O100 -> 3798 | H100: =F100*O100 -> 2198 | I100: =(E100*K100)*O100 -> 1595.16 | J100: =H100-G100 -> -1600 | K100: 0.42 | L100: 4.5 | M100: 22420 | N100: MOINUL H.,Jayendra | O100: =LEN(N100)-LEN(SUBSTITUTE(N100,",",""))+1 -> 2 | P100: =HYPERLINK(#REF!,"Link") -> #REF! | Q100: =HYPERLINK(#REF!,"Link") -> #REF!
A101: B08CHKQ8D4 | B101: Wayona Type C to | C101: LaptopAccessories | E101: 1499 | F101: 719 | G101: =E101*O101 -> 2998 | H101: =F101*O101 -> 1438 | I101: =(E101*K101)*O101 -> 1558.96 | J101: =H101-G101 -> -1560 | K101: 0.52 | L101: 4.1 | M101: 1045 | N101: Kiran Kolla,Vishal | O101: =LEN(N101)-LEN(SUBSTITUTE(N101,",",""))+1 -> 2 | P101: =HYPERLINK(#REF!,"Link") -> #REF! | Q101: =HYPERLINK(#REF!,"Link") -> #REF!
A102: B09BW334ML | B102: Dealfreez Case Compatible with | C102: TabletAccessories | D102: Stands | E102: 1499 | F102: 349 | G102: =E102*O102 -> 2998 | H102: =F102*O102 -> 698 | I102: =(E102*K102)*O102 -> 2308.46 | J102: =H102-G102 -> -2300 | K102: 0.77 | L102: 4.3 | M102: 4145 | N102: parvinder singh,Rishikesh | O102: =LEN(N102)-LEN(SUBSTITUTE(N102,",",""))+1 -> 2 | P102: =HYPERLINK(#REF!,"Link") -> #REF! | Q102: =HYPERLINK(#REF!,"Link") -> #REF!
A103: B082T6GVLJ | B103: Amazon Basics New Release | C103: Adapters&Multi-Outlets | E103: 1809 | F103: 849 | G103: =E103*O103 -> 3618 | H103: =F103*O103 -> 1698 | I103: =(E103*K103)*O103 -> 1917.54 | J103: =H103-G103 -> -1920 | K103: 0.53 | L103: 4.3 | M103: 6547 | N103: Ananya S.,Anirban | O103: =LEN(N103)-LEN(SUBSTITUTE(N103,",",""))+1 -> 2 | P103: =HYPERLINK(#REF!,"Link") -> #REF! | Q103: =HYPERLINK(#REF!,"Link") -> #REF!
A104: B07DL1KC3H | B104: Isoelite Remote Compatible for | C104: Paper | D104: Copy&PrintingPaper | E104: 899 | F104: 299 | G104: =E104*O104 -> 3596 | H104: =F104*O104 -> 1196 | I104: =(E104*K104)*O104 -> 2409.32 | J104: =H104-G104 -> -2400 | K104: 0.67 | L104: 4 | M104: 1588 | N104: Pritam Roy,AdyZon,pradeep4uall,purnendu | O104: =LEN(N104)-LEN(SUBSTITUTE(N104,",",""))+1 -> 4 | P104: =HYPERLINK(#REF!,"Link") -> #REF! | Q104: =HYPERLINK(#REF!,"Link") -> #REF!
A105: B0B6F98KJJ | B105: MI 100 cm | C105: InternalSolidStateDrives | E105: 29999 | F105: 21999 | G105: =E105*O105 -> 59998 | H105: =F105*O105 -> 43998 | I105: =(E105*K105)*O105 -> 16199.46 | J105: =H105-G105 -> -16000 | K105: 0.27 | L105: 4.2 | M105: 32840 | N105: Manoj maddheshiya,Manoj | O105: =LEN(N105)-LEN(SUBSTITUTE(N105,",",""))+1 -> 2 | P105: =HYPERLINK(#REF!,"Link") -> #REF! | Q105: =HYPERLINK(#REF!,"Link") -> #REF!
A106: B07JNVF678 | B106: Wayona Nylon Braided USB | C106: Speakers | D106: MultimediaSpeakerSystems | E106: 999 | F106: 349 | G106: =E106*O106 -> 3996 | H106: =F106*O106 -> 1396 | I106: =(E106*K106)*O106 -> 2597.4 | J106: =H106-G106 -> -2600 | K106: 0.65 | L106: 4.2 | M106: 13120 | N106: Pratik,Amazon Customer,Abhishek,Derrick | O106: =LEN(N106)-LEN(SUBSTITUTE(N106,",",""))+1 -> 4 | P106: =HYPERLINK(#REF!,"Link") -> #REF! | Q106: =HYPERLINK(#REF!,"Link") -> #REF!
A107: B09QGZFBPM | B107: Wayona Type C To | C107: DataCards&Dongles | E107: 999 | F107: 399 | G107: =E107*O107 -> 2997 | H107: =F107*O107 -> 1197 | I107: =(E107*K107)*O107 -> 1798.2 | J107: =H107-G107 -> -1800 | K107: 0.6 | L107: 4.3 | M107: 2806 | N107: sameer Dubey,virender,Amazon | O107: =LEN(N107)-LEN(SUBSTITUTE(N107,",",""))+1 -> 3 | P107: =HYPERLINK(#REF!,"Link") -> #REF! | Q107: =HYPERLINK(#REF!,"Link") -> #REF!
A108: B07JGDB5M1 | B108: Wayona Nylon Braided 2M | C108: LaptopAccessories | D108: LaptopChargers&PowerSupplies | E108: 1299 | F108: 449 | G108: =E108*O108 -> 5196 | H108: =F108*O108 -> 1796 | I108: =(E108*K108)*O108 -> 3377.4 | J108: =H108-G108 -> -3400 | K108: 0.65 | L108: 4.2 | M108: 24269 | N108: Manav,Adarsh gupta,Sundeep,S.Sayeed | O108: =LEN(N108)-LEN(SUBSTITUTE(N108,",",""))+1 -> 4 | P108: =HYPERLINK(#REF!,"Link") -> #REF! | Q108: =HYPERLINK(#REF!,"Link") -> #REF!
...

Sheet DASHBOARD
G1: CATEGORY WISE AVG DISCOUNT PERCENTAGE | T1: CATEGORY WISE RATING
AK11: COUNT OF CATEGOTY
I19: AVG PRICE OF EACH CATEGORY
T21: AVG PRICE AND AVG RATING

Sheet ANALYSIS
C1: ANALYSIS
A2: total product | H2: LIMITATIONS
A3: 1466 | C3: AVERAGE SELLING PRICE | E3: =AVERAGE(DATASET!F:F) -> 3125.3109
C4: Total Products | E4: 1466 | H4: The dataset does not include Units Sold.
H5: Brand information is limited.
C6: Avg Discount % | E6: =AVERAGE(DATASET!K:K) -> 0.47691468 | H6: Revenue and Profit cannot be calculated accurately.
C7: Avg Rating | E7: =AVERAGE(DATASET!L:L) -> 4.0965847 | H7: Estimated Revenue Potential is based on Rating Count.
C8: Total Reviews | E8: =SUM(DATASET!M:M) -> 26766377 | H8: Analysis focuses on product performance rather than actual financial performance.
C9: HIGHEST REVIEW | E9: =K18 -> 426973
C10: PRODUCT | E10: =L18 -> AmazonBasics Flexible Premium HDMI
B12: expected revenue | C12: actual revenue | D12: gross margin
B13: =SUM(DATASET!G:G) -> 22879163 | C13: =SUM(DATASET!H:H) -> 13062023 | D13: =C13-B13 -> -9817140.1 | J13: CORRELATION BETWWEN REVIEW COUNT AND RATINGS
D14: =(D13)/B13*100 -> -42.90865 | J14: =CORREL(DATASET!M:M,DATASET!L:L) -> 0.10223482
B17: correlation between discount and price of product | F17: trigger | G17: value | H17: product | J17: review | L17: PRODUCT
B18: =CORREL(DATASET!K:K,DATASET!L:L) -> -0.15537544 | F18: max price | G18: =MAX(DATASET!F:F) -> 77990 | H18: =_xlfn.XLOOKUP(G18,DATASET!$F:$F,DATASET!$B:$B) -> Sony Bravia 164 cm | J18: max | K18: =MAX(DATASET!M:M) -> 426973 | L18: =_xlfn.XLOOKUP(ANALYSIS!K18,DATASET!M:M,DATASET!B:B,) -> AmazonBasics Flexible Premium HDMI | M18: =_xlfn.XLOOKUP(K18,DATASET!M:M,DATASET!L:L) -> 4.4
F19: min price | G19: =MIN(DATASET!F:F) -> 39 | H19: =_xlfn.XLOOKUP(G19,DATASET!$F:$F,DATASET!$B:$B) -> GIZGA essentials Universal Silicone | J19: min | K19: =MIN(DATASET!M:M) -> 2 | L19: =_xlfn.XLOOKUP(ANALYSIS!K19,DATASET!M:M,DATASET!B:B,) -> Khaitan ORFin Fan heater | M19: =_xlfn.XLOOKUP(K19,DATASET!M:M,DATASET!L:L) -> 2
B20: correlation between discounting rate and profit nad loss | F20: max rating | G20: =MAX(DATASET!L:L) -> 5
B21: =CORREL(DATASET!I:I,DATASET!J:J) -> -0.9999761 | F21: min rating | G21: =MIN(DATASET!L:L) -> 2
B23: =CORREL(DATASET!M:M,DATASET!L:L) -> 0.10223482

Sheet Sheet6
A4: Row Labels | B4: Count of Product | E4: Average Price by Category (Column Chart)
A5: Accessories | B5: 123 | E5: Average Discount by Category (Bar Chart)
A6: Adapters | B6: 15 | E6: Rating Distribution (Histogram/Column)
A7: Adapters&Multi-Outlets | B7: 7 | E7: Price vs Rating (Scatter Plot)
A8: AirConditioners | B8: 7 | E8: Top 10 Most Reviewed Products (Bar Chart)
A9: AirPurifiers | B9: 7 | E9: Product Count by Category (Pie or Doughnut Chart)
A10: Audio&VideoAccessories | B10: 28
A11: AVReceivers&Amplifiers | B11: 8
A12: Cables&Accessories | B12: 38
A13: Calculators | B13: 22
A14: Cases | B14: 7
A15: Coffee,Tea&Espresso | B15: 49
A16: Condenser | B16: 8
A17: CordManagement | B17: 7
A18: DataCards&Dongles | B18: 7
A19: DisposableBatteries | B19: 8
A20: Drawing&PaintingSupplies | B20: 7
A21: DrawingMaterials | B21: 14
... A77: Grand Total | B77: 1465

Sheet Sheet1
A2: Row Labels | B2: Average of actual_price | C2: Average of discounted_price | D2: Average of discount_percentage | E2: Average of rating
A3: Row Labels | B3: Count of Product | C3: Count of product type
A4: AVReceivers&Amplifiers | B4: 8
A5: Grand Total | B5: 8

Sheet Sheet12
A1: Row Labels | B1: Average of discounted_price | C1: Average of rating
A2: Accessories | B2: 4271.1644 | C2: 4.0875
A3: Adapters | B3: 10089 | C3: 4.15
A4: Adapters&Multi-Outlets | B4: 849 | C4: 4.3
A5: AirConditioners | B5: 8990 | C5: 3.9
A6: AirPurifiers | B6: 1399 | C6: 4.4
A7: Audio&VideoAccessories | B7: 7961 | C7: 4.1
A8: AVReceivers&Amplifiers | B8: 13999 | C8: 4.2
A9: Cables&Accessories | B9: 5307.2 | C9: 4.28
A10: Calculators | B10: 10192 | C10: 4.2333333
A11: Cases | B11: 18990 | C11: 4.2
A12: Coffee,Tea&Espresso | B12: 7242 | C12: 4.0571429
A13: Condenser | B13: 1199 | C13: 4.4
... A72: WaterPurifiers&Accessories | B72: 11245.667 | C72: 4.1666667
B73: 2955.2613 | C73: 4.0908589
C74: 4.0965847

Sheet Sheet5
A1: Row Labels | B1: Average of discount_percentage
A2: AVReceivers&Amplifiers | B2: 0.47
A3: Grand Total | B3: 0.47
F44: Row Labels | G44: Average of rating
F45: Accessories | G45: 4.1227642
F46: Adapters | G46: 3.9333333
F47: Adapters&Multi-Outlets | G47: 4.1428571
F48: AirConditioners | G48: 3.9714286
F49: AirPurifiers | G49: 4.2285714
F50: Audio&VideoAccessories | G50: 4.05
F51: AVReceivers&Amplifiers | G51: 4.0625
F52: Cables&Accessories | G52: 4.1026316
F53: Calculators | G53: 4.1428571
F54: Cases | G54: 4.0142857
F55: Coffee,Tea&Espresso | G55: 4.1326531
F56: Condenser | G56: 4.15
... F117: Grand Total | G117: 4.0965847

Sheet Sheet10
A1: Row Labels | B1: Average of discounted_price
A2: Accessories | B2: 2817.6446
A3: Adapters | B3: 2594.8
A4: Adapters&Multi-Outlets | B4: 3210.7143
A5: AirConditioners | B5: 5144.8571
A6: AirPurifiers | B6: 6257.2857
A7: Audio&VideoAccessories | B7: 4313.6071
A8: AVReceivers&Amplifiers | B8: 4222.625
A9: Cables&Accessories | B9: 3509.2105
A10: Calculators | B10: 5901.1364
A11: Cases | B11: 4237.1429
A12: Coffee,Tea&Espresso | B12: 2213.5918
A13: Condenser | B13: 11555.5
... A74: Grand Total | B74: 3125.3109

Sheet Sheet11
A1: Row Labels | B1: Average of discounted_price | C1: Average of rating
A2: Accessories | B2: 2817.6446 | C2: 4.1227642
A3: Adapters | B3: 2594.8 | C3: 3.9333333
A4: Adapters&Multi-Outlets | B4: 3210.7143 | C4: 4.1428571
A5: AirConditioners | B5: 5144.8571 | C5: 3.9714286
A6: AirPurifiers | B6: 6257.2857 | C6: 4.2285714
A7: Audio&VideoAccessories | B7: 4313.6071 | C7: 4.05
A8: AVReceivers&Amplifiers | B8: 4222.625 | C8: 4.0625
A9: Cables&Accessories | B9: 3509.2105 | C9: 4.1026316
A10: Calculators | B10: 5901.1364 | C10: 4.1428571
A11: Cases | B11: 4237.1429 | C11: 4.0142857
A12: Coffee,Tea&Espresso | B12: 2213.5918 | C12: 4.1326531
A13: Condenser | B13: 11555.5 | C13: 4.15
... A74: Grand Total | B74: 3125.3109 | C74: 4.0965847

Sheet Sheet14
A1: Row Labels | B1: Average of discount_percentage
A2: Accessories | B2: 0.47804878
A3: Adapters | B3: 0.46933333
A4: Adapters&Multi-Outlets | B4: 0.44571429
A5: AirConditioners | B5: 0.38
A6: AirPurifiers | B6: 0.40714286
A7: Audio&VideoAccessories | B7: 0.49
A8: AVReceivers&Amplifiers | B8: 0.47
A9: Cables&Accessories | B9: 0.47315789
A10: Calculators | B10: 0.46727273
A11: Cases | B11: 0.51428571
A12: Coffee,Tea&Espresso | B12: 0.50530612
A13: Condenser | B13: 0.49625
... A74: Grand Total | B74: 0.47691468
